clean_logging/__init__.py
clean_logging/core/__init__.py
clean_logging/core/interfaces/__init__.py
clean_logging/core/interfaces/log_repository_interface.py
clean_logging/infrastructure/__init__.py
clean_logging/infrastructure/logging_setup.py
clean_logging/infrastructure/repositories/__init__.py
clean_logging/infrastructure/repositories/file_log_repository.py
clean_logging-0.9.3.dist-info/licenses/LICENSE
clean_logging-0.9.3.dist-info/METADATA
clean_logging-0.9.3.dist-info/WHEEL
clean_logging-0.9.3.dist-info/top_level.txt
clean_logging-0.9.3.dist-info/RECORD
