Metadata-Version: 2.4
Name: clean_logging
Version: 0.9.3
Summary: A clean and modular logging package
Author-email: qasem <qasemt@gmail.com>
License: MIT
Classifier: Programming Language :: Python :: 3
Classifier: License :: OSI Approved :: MIT License
Classifier: Operating System :: OS Independent
Requires-Python: >=3.8
License-File: LICENSE
Requires-Dist: coloredlogs>=15.0
Requires-Dist: pytz
Dynamic: license-file
